LICENSE.txt
README.md
setup.cfg
setup.py
kyodo/__init__.py
kyodo/client.py
kyodo.egg-info/PKG-INFO
kyodo.egg-info/SOURCES.txt
kyodo.egg-info/dependency_links.txt
kyodo.egg-info/requires.txt
kyodo.egg-info/top_level.txt
kyodo/api/__init__.py
kyodo/api/account.py
kyodo/api/auth.py
kyodo/api/base.py
kyodo/api/chats.py
kyodo/api/circles.py
kyodo/api/common.py
kyodo/api/posts.py
kyodo/api/stickers.py
kyodo/api/store.py
kyodo/api/users.py
kyodo/objects/BaseEvent.py
kyodo/objects/__init__.py
kyodo/objects/broadcast.py
kyodo/objects/chat.py
kyodo/objects/chat_message.py
kyodo/objects/circle.py
kyodo/objects/feed.py
kyodo/objects/folders.py
kyodo/objects/health_services.py
kyodo/objects/homefeed_explore.py
kyodo/objects/meetings.py
kyodo/objects/notif.py
kyodo/objects/operation_logs.py
kyodo/objects/posts.py
kyodo/objects/referral_code.py
kyodo/objects/reports.py
kyodo/objects/share_link.py
kyodo/objects/stickers.py
kyodo/objects/store.py
kyodo/objects/topics.py
kyodo/objects/user.py
kyodo/objects/args/__init__.py
kyodo/objects/args/chat.py
kyodo/objects/args/circle.py
kyodo/objects/args/event_type.py
kyodo/objects/args/object_types.py
kyodo/objects/args/store.py
kyodo/objects/args/upload_media.py
kyodo/utils/__init__.py
kyodo/utils/constants.py
kyodo/utils/exceptions.py
kyodo/utils/generators.py
kyodo/utils/logger.py
kyodo/utils/request_helper.py
kyodo/utils/requester.py
kyodo/ws/__init__.py
kyodo/ws/socket.py
kyodo/ws/socket_handler.py