Metadata-Version: 2.4
Name: kyodo
Version: 1.0
Summary: Library for creating kyodo bots and scripts.
Home-page: https://github.com/alx0rr/kyodo
Download-URL: https://github.com/alx0rr/kyodo/archive/refs/heads/main.zip
Author: alx0rr
Author-email: anon.mail.al@proton.me
License: MIT
Keywords: kyodo.py,kyodo,kyodo-py,kyodo-bot,api,python,python3,python3.x,alx0rr,official,async
License-File: LICENSE.txt
Requires-Dist: logging
Requires-Dist: colorama
Requires-Dist: aiohttp
Requires-Dist: pyjwt
Requires-Dist: aiofiles
Requires-Dist: orjson
Dynamic: author
Dynamic: author-email
Dynamic: description
Dynamic: description-content-type
Dynamic: download-url
Dynamic: home-page
Dynamic: keywords
Dynamic: license
Dynamic: license-file
Dynamic: requires-dist
Dynamic: summary
